[{"pen":false,"bukkit":false,"mouseDown":false,"mouseUp":false,"move":false,"color":"193, 193, 193","target":null,"letter":null},{"pen":false,"bukkit":true,"mouseDown":false,"mouseUp":false,"move":false,"color":null,"target":null,"letter":null},{"pen":false,"bukkit":false,"mouseDown":false,"mouseUp":false,"move":true,"color":null,"target":"48, 428","letter":null},{"pen":false,"bukkit":false,"mouseDown":true,"mouseUp":false,"move":false,"color":null,"target":null,"letter":null},{"pen":false,"bukkit":false,"mouseDown":false,"mouseUp":false,"move":true,"color":null,"target":"48, 428","letter":null},{"pen":false,"bukkit":false,"mouseDown":false,"mouseUp":true,"move":false,"color":null,"target":null,"letter":null},{"pen":false,"bukkit":false,"mouseDown":false,"mouseUp":false,"move":false,"color":"232, 162, 0","target":null,"letter":null},{"pen":true,"bukkit":false,"mouseDown":false,"mouseUp":false,"move":false,"color":null,"target":null,"letter":null},{"pen":false,"bukkit":false,"mouseDown":false,"mouseUp":false,"move":true,"color":null,"target":"251, 154","letter":null},{"pen":false,"bukkit":false,"mouseDown":true,"mouseUp":false,"move":false,"color":null,"target":null,"letter":null},{"pen":false,"bukkit":false,"mouseDown":false,"mouseUp":false,"move":true,"color":null,"target":"242, 161","letter":null},{"pen":false,"bukkit":false,"mouseDown":false,"mouseUp":false,"move":true,"color":null,"target":"233, 168","letter":null},{"pen":false,"bukkit":false,"mouseDown":false,"mouseUp":false,"move":true,"color":null,"target":"223, 175","letter":null},{"pen":false,"bukkit":false,"mouseDown":false,"mouseUp":false,"move":true,"color":null,"target":"213, 182","letter":null},{"pen":false,"bukkit":false,"mouseDown":false,"mouseUp":false,"move":true,"color":null,"target":"204, 189","letter":null},{"pen":false,"bukkit":false,"mouseDown":false,"mouseUp":false,"move":true,"color":null,"target":"194, 195","letter":null},{"pen":false,"bukkit":false,"mouseDown":false,"mouseUp":false,"move":true,"color":null,"target":"184, 201","letter":null},{"pen":false,"bukkit":false,"mouseDown":false,"mouseUp":false,"move":true,"color":null,"target":"174, 208","letter":null},{"pen":false,"bukkit":false,"mouseDown":false,"mouseUp":false,"move":true,"color":null,"target":"165, 215","letter":null},{"pen":false,"bukkit":false,"mouseDown":false,"mouseUp":false,"move":true,"color":null,"target":"156, 222","letter":null},{"pen":false,"bukkit":false,"mouseDown":false,"mouseUp":false,"move":true,"color":null,"target":"147, 230","letter":null},{"pen":false,"bukkit":false,"mouseDown":false,"mouseUp":false,"move":true,"color":null,"target":"137, 236","letter":null},{"pen":false,"bukkit":false,"mouseDown":false,"mouseUp":false,"move":true,"color":null,"target":"127, 242","letter":null},{"pen":false,"bukkit":false,"mouseDown":false,"mouseUp":false,"move":true,"color":null,"target":"117, 247","letter":null},{"pen":false,"bukkit":false,"mouseDown":false,"mouseUp":false,"move":true,"color":null,"target":"107, 252","letter":null},{"pen":false,"bukkit":false,"mouseDown":false,"mouseUp":false,"move":true,"color":null,"target":"97, 257","letter":null},{"pen":false,"bukkit":false,"mouseDown":false,"mouseUp":false,"move":true,"color":null,"target":"88, 264","letter":null},{"pen":false,"bukkit":false,"mouseDown":false,"mouseUp":false,"move":true,"color":null,"target":"94, 274","letter":null},{"pen":false,"bukkit":false,"mouseDown":false,"mouseUp":false,"move":true,"color":null,"target":"101, 283","letter":null},{"pen":false,"bukkit":false,"mouseDown":false,"mouseUp":false,"move":true,"color":null,"target":"108, 292","letter":null},{"pen":false,"bukkit":false,"mouseDown":false,"mouseUp":false,"move":true,"color":null,"target":"115, 301","letter":null},{"pen":false,"bukkit":false,"mouseDown":false,"mouseUp":false,"move":true,"color":null,"target":"122, 310","letter":null},{"pen":false,"bukkit":false,"mouseDown":false,"mouseUp":false,"move":true,"color":null,"target":"133, 310","letter":null},{"pen":false,"bukkit":false,"mouseDown":false,"mouseUp":false,"move":true,"color":null,"target":"134, 299","letter":null},{"pen":false,"bukkit":false,"mouseDown":false,"mouseUp":false,"move":true,"color":null,"target":"126, 291","letter":null},{"pen":false,"bukkit":false,"mouseDown":false,"mouseUp":false,"move":true,"color":null,"target":"121, 281","letter":null},{"pen":false,"bukkit":false,"mouseDown":false,"mouseUp":false,"move":true,"color":null,"target":"125, 270","letter":null},{"pen":false,"bukkit":false,"mouseDown":false,"mouseUp":false,"move":true,"color":null,"target":"136, 271","letter":null},{"pen":false,"bukkit":false,"mouseDown":false,"mouseUp":false,"move":true,"color":null,"target":"142, 281","letter":null},{"pen":false,"bukkit":false,"mouseDown":false,"mouseUp":false,"move":true,"color":null,"target":"153, 277","letter":null},{"pen":false,"bukkit":false,"mouseDown":false,"mouseUp":false,"move":true,"color":null,"target":"151, 266","letter":null},{"pen":false,"bukkit":false,"mouseDown":false,"mouseUp":false,"move":true,"color":null,"target":"154, 255","letter":null},{"pen":false,"bukkit":false,"mouseDown":false,"mouseUp":false,"move":true,"color":null,"target":"164, 250","letter":null},{"pen":false,"bukkit":false,"mouseDown":false,"mouseUp":false,"move":true,"color":null,"target":"172, 258","letter":null},{"pen":false,"bukkit":false,"mouseDown":false,"mouseUp":false,"move":true,"color":null,"target":"180, 266","letter":null},{"pen":false,"bukkit":false,"mouseDown":false,"mouseUp":false,"move":true,"color":null,"target":"185, 276","letter":null},{"pen":false,"bukkit":false,"mouseDown":false,"mouseUp":false,"move":true,"color":null,"target":"196, 274","letter":null},{"pen":false,"bukkit":false,"mouseDown":false,"mouseUp":false,"move":true,"color":null,"target":"201, 264","letter":null},{"pen":false,"bukkit":false,"mouseDown":false,"mouseUp":false,"move":true,"color":null,"target":"194, 255","letter":null},{"pen":false,"bukkit":false,"mouseDown":false,"mouseUp":false,"move":true,"color":null,"target":"199, 245","letter":null},{"pen":false,"bukkit":false,"mouseDown":false,"mouseUp":false,"move":true,"color":null,"target":"210, 247","letter":null},{"pen":false,"bukkit":false,"mouseDown":false,"mouseUp":false,"move":true,"color":null,"target":"220, 252","letter":null},{"pen":false,"bukkit":false,"mouseDown":false,"mouseUp":false,"move":true,"color":null,"target":"224, 241","letter":null},{"pen":false,"bukkit":false,"mouseDown":false,"mouseUp":false,"move":true,"color":null,"target":"215, 234","letter":null},{"pen":false,"bukkit":false,"mouseDown":false,"mouseUp":false,"move":true,"color":null,"target":"207, 226","letter":null},{"pen":false,"bukkit":false,"mouseDown":false,"mouseUp":false,"move":true,"color":null,"target":"214, 217","letter":null},{"pen":false,"bukkit":false,"mouseDown":false,"mouseUp":false,"move":true,"color":null,"target":"224, 211","letter":null},{"pen":false,"bukkit":false,"mouseDown":false,"mouseUp":false,"move":true,"color":null,"target":"233, 204","letter":null},{"pen":false,"bukkit":false,"mouseDown":false,"mouseUp":false,"move":true,"color":null,"target":"242, 197","letter":null},{"pen":false,"bukkit":false,"mouseDown":false,"mouseUp":false,"move":true,"color":null,"target":"251, 189","letter":null},{"pen":false,"bukkit":false,"mouseDown":false,"mouseUp":false,"move":true,"color":null,"target":"260, 182","letter":null},{"pen":false,"bukkit":false,"mouseDown":false,"mouseUp":false,"move":true,"color":null,"target":"268, 174","letter":null},{"pen":false,"bukkit":false,"mouseDown":false,"mouseUp":false,"move":true,"color":null,"target":"277, 167","letter":null},{"pen":false,"bukkit":false,"mouseDown":false,"mouseUp":false,"move":true,"color":null,"target":"286, 160","letter":null},{"pen":false,"bukkit":false,"mouseDown":false,"mouseUp":false,"move":true,"color":null,"target":"294, 152","letter":null},{"pen":false,"bukkit":false,"mouseDown":false,"mouseUp":false,"move":true,"color":null,"target":"303, 145","letter":null},{"pen":false,"bukkit":false,"mouseDown":false,"mouseUp":false,"move":true,"color":null,"target":"311, 137","letter":null},{"pen":false,"bukkit":false,"mouseDown":false,"mouseUp":false,"move":true,"color":null,"target":"319, 129","letter":null},{"pen":false,"bukkit":false,"mouseDown":false,"mouseUp":false,"move":true,"color":null,"target":"330, 128","letter":null},{"pen":false,"bukkit":false,"mouseDown":false,"mouseUp":false,"move":true,"color":null,"target":"341, 132","letter":null},{"pen":false,"bukkit":false,"mouseDown":false,"mouseUp":false,"move":true,"color":null,"target":"352, 133","letter":null},{"pen":false,"bukkit":false,"mouseDown":false,"mouseUp":false,"move":true,"color":null,"target":"363, 133","letter":null},{"pen":false,"bukkit":false,"mouseDown":false,"mouseUp":false,"move":true,"color":null,"target":"373, 128","letter":null},{"pen":false,"bukkit":false,"mouseDown":false,"mouseUp":false,"move":true,"color":null,"target":"382, 121","letter":null},{"pen":false,"bukkit":false,"mouseDown":false,"mouseUp":false,"move":true,"color":null,"target":"389, 112","letter":null},{"pen":false,"bukkit":false,"mouseDown":false,"mouseUp":false,"move":true,"color":null,"target":"393, 101","letter":null},{"pen":false,"bukkit":false,"mouseDown":false,"mouseUp":false,"move":true,"color":null,"target":"394, 90","letter":null},{"pen":false,"bukkit":false,"mouseDown":false,"mouseUp":false,"move":true,"color":null,"target":"391, 79","letter":null},{"pen":false,"bukkit":false,"mouseDown":false,"mouseUp":false,"move":true,"color":null,"target":"385, 69","letter":null},{"pen":false,"bukkit":false,"mouseDown":false,"mouseUp":false,"move":true,"color":null,"target":"376, 62","letter":null},{"pen":false,"bukkit":false,"mouseDown":false,"mouseUp":false,"move":true,"color":null,"target":"367, 55","letter":null},{"pen":false,"bukkit":false,"mouseDown":false,"mouseUp":false,"move":true,"color":null,"target":"357, 50","letter":null},{"pen":false,"bukkit":false,"mouseDown":false,"mouseUp":false,"move":true,"color":null,"target":"346, 47","letter":null},{"pen":false,"bukkit":false,"mouseDown":false,"mouseUp":false,"move":true,"color":null,"target":"335, 46","letter":null},{"pen":false,"bukkit":false,"mouseDown":false,"mouseUp":false,"move":true,"color":null,"target":"324, 46","letter":null},{"pen":false,"bukkit":false,"mouseDown":false,"mouseUp":false,"move":true,"color":null,"target":"314, 51","letter":null},{"pen":false,"bukkit":false,"mouseDown":false,"mouseUp":false,"move":true,"color":null,"target":"306, 59","letter":null},{"pen":false,"bukkit":false,"mouseDown":false,"mouseUp":false,"move":true,"color":null,"target":"303, 70","letter":null},{"pen":false,"bukkit":false,"mouseDown":false,"mouseUp":false,"move":true,"color":null,"target":"303, 81","letter":null},{"pen":false,"bukkit":false,"mouseDown":false,"mouseUp":false,"move":true,"color":null,"target":"304, 92","letter":null},{"pen":false,"bukkit":false,"mouseDown":false,"mouseUp":false,"move":true,"color":null,"target":"308, 103","letter":null},{"pen":false,"bukkit":false,"mouseDown":false,"mouseUp":false,"move":true,"color":null,"target":"311, 114","letter":null},{"pen":false,"bukkit":false,"mouseDown":false,"mouseUp":false,"move":true,"color":null,"target":"302, 121","letter":null},{"pen":false,"bukkit":false,"mouseDown":false,"mouseUp":false,"move":true,"color":null,"target":"292, 127","letter":null},{"pen":false,"bukkit":false,"mouseDown":false,"mouseUp":false,"move":true,"color":null,"target":"284, 135","letter":null},{"pen":false,"bukkit":false,"mouseDown":false,"mouseUp":false,"move":true,"color":null,"target":"274, 141","letter":null},{"pen":false,"bukkit":false,"mouseDown":false,"mouseUp":false,"move":true,"color":null,"target":"264, 147","letter":null},{"pen":false,"bukkit":false,"mouseDown":false,"mouseUp":false,"move":true,"color":null,"target":"253, 151","letter":null},{"pen":false,"bukkit":false,"mouseDown":false,"mouseUp":false,"move":true,"color":null,"target":"243, 156","letter":null},{"pen":false,"bukkit":false,"mouseDown":false,"mouseUp":false,"move":true,"color":null,"target":"240, 159","letter":null},{"pen":false,"bukkit":false,"mouseDown":false,"mouseUp":true,"move":false,"color":null,"target":null,"letter":null},{"pen":false,"bukkit":false,"mouseDown":false,"mouseUp":false,"move":true,"color":null,"target":"318, 79","letter":null},{"pen":false,"bukkit":false,"mouseDown":true,"mouseUp":false,"move":false,"color":null,"target":null,"letter":null},{"pen":false,"bukkit":false,"mouseDown":false,"mouseUp":false,"move":true,"color":null,"target":"318, 90","letter":null},{"pen":false,"bukkit":false,"mouseDown":false,"mouseUp":false,"move":true,"color":null,"target":"324, 100","letter":null},{"pen":false,"bukkit":false,"mouseDown":false,"mouseUp":false,"move":true,"color":null,"target":"334, 106","letter":null},{"pen":false,"bukkit":false,"mouseDown":false,"mouseUp":false,"move":true,"color":null,"target":"343, 113","letter":null},{"pen":false,"bukkit":false,"mouseDown":false,"mouseUp":false,"move":true,"color":null,"target":"353, 118","letter":null},{"pen":false,"bukkit":false,"mouseDown":false,"mouseUp":false,"move":true,"color":null,"target":"364, 116","letter":null},{"pen":false,"bukkit":false,"mouseDown":false,"mouseUp":false,"move":true,"color":null,"target":"372, 108","letter":null},{"pen":false,"bukkit":false,"mouseDown":false,"mouseUp":false,"move":true,"color":null,"target":"378, 98","letter":null},{"pen":false,"bukkit":false,"mouseDown":false,"mouseUp":false,"move":true,"color":null,"target":"381, 87","letter":null},{"pen":false,"bukkit":false,"mouseDown":false,"mouseUp":false,"move":true,"color":null,"target":"373, 79","letter":null},{"pen":false,"bukkit":false,"mouseDown":false,"mouseUp":false,"move":true,"color":null,"target":"365, 71","letter":null},{"pen":false,"bukkit":false,"mouseDown":false,"mouseUp":false,"move":true,"color":null,"target":"355, 65","letter":null},{"pen":false,"bukkit":false,"mouseDown":false,"mouseUp":false,"move":true,"color":null,"target":"345, 60","letter":null},{"pen":false,"bukkit":false,"mouseDown":false,"mouseUp":false,"move":true,"color":null,"target":"334, 60","letter":null},{"pen":false,"bukkit":false,"mouseDown":false,"mouseUp":false,"move":true,"color":null,"target":"323, 61","letter":null},{"pen":false,"bukkit":false,"mouseDown":false,"mouseUp":false,"move":true,"color":null,"target":"322, 72","letter":null},{"pen":false,"bukkit":false,"mouseDown":false,"mouseUp":false,"move":true,"color":null,"target":"319, 83","letter":null},{"pen":false,"bukkit":false,"mouseDown":false,"mouseUp":false,"move":true,"color":null,"target":"319, 89","letter":null},{"pen":false,"bukkit":false,"mouseDown":false,"mouseUp":true,"move":false,"color":null,"target":null,"letter":null},{"pen":false,"bukkit":false,"mouseDown":false,"mouseUp":false,"move":false,"color":"255, 228, 0","target":null,"letter":null},{"pen":false,"bukkit":true,"mouseDown":false,"mouseUp":false,"move":false,"color":null,"target":null,"letter":null},{"pen":false,"bukkit":false,"mouseDown":false,"mouseUp":false,"move":true,"color":null,"target":"181, 232","letter":null},{"pen":false,"bukkit":false,"mouseDown":true,"mouseUp":false,"move":false,"color":null,"target":null,"letter":null},{"pen":false,"bukkit":false,"mouseDown":false,"mouseUp":false,"move":true,"color":null,"target":"181, 232","letter":null},{"pen":false,"bukkit":false,"mouseDown":false,"mouseUp":true,"move":false,"color":null,"target":null,"letter":null}]